{
  "lessons": [
    {
      "date": "settembre 2023",
      "title": "SISTEMA DI COMUNICAZIONE",
      "text": "1.html",
      "text_made_by": "Legnani Matteo",
      "questions": "1_questions.json"
    },
    {
      "date": "settembre 2023",
      "title": "COMPONENTI",
      "text": "2.html",
      "text_made_by": "legnani Matteo",
      "questions": "2_questions.json"
    },
    {
      "date": "ottobre 2023",
      "title": "TIPI DI COMPONENTI",
      "text": "3.html",
      "text_made_by": "legnani Matteo",
      "questions": "3_questions.json"
    }
  ]
}  